nominopolitan/__init__.py
nominopolitan/apps.py
nominopolitan/mixins.py
nominopolitan/templates/nominopolitan/base.html
nominopolitan/templates/nominopolitan/object_confirm_delete.html
nominopolitan/templates/nominopolitan/object_detail.html
nominopolitan/templates/nominopolitan/object_form.html
nominopolitan/templates/nominopolitan/object_list.html
nominopolitan/templates/nominopolitan/partial/detail.html
nominopolitan/templates/nominopolitan/partial/list.html
nominopolitan/templatetags/__init__.py
nominopolitan/templatetags/nominopolitan.py
django_nominopolitan-0.7.0.dist-info/LICENSE
django_nominopolitan-0.7.0.dist-info/METADATA
django_nominopolitan-0.7.0.dist-info/WHEEL
django_nominopolitan-0.7.0.dist-info/RECORD
