Metadata-Version: 2.1
Name: django-nominopolitan
Version: 0.7.0
Summary: Neapolitan with namespaces - Django CRUD views
Home-page: https://github.com/doctor-cornelius/django-nominopolitan
Author: Michael Foulds
Author-email: mfoulds@navigatus.net
Requires-Python: >=3.12.3,<4.0.0
Classifier: Programming Language :: Python :: 3
Classifier: Programming Language :: Python :: 3.13
Requires-Dist: django (>=5.1.3,<6.0.0)
Requires-Dist: django-htmx (>=1.21.0,<2.0.0)
Requires-Dist: django-template-partials (>=24.4,<25.0)
Project-URL: Repository, https://github.com/doctor-cornelius/django-nominopolitan
